click_from_docstring.py
click_from_docstring-0.1.0a1.dist-info/LICENSE
click_from_docstring-0.1.0a1.dist-info/METADATA
click_from_docstring-0.1.0a1.dist-info/WHEEL
click_from_docstring-0.1.0a1.dist-info/top_level.txt
click_from_docstring-0.1.0a1.dist-info/RECORD
