Metadata-Version: 2.1
Name: click-from-docstring
Version: 0.1.0a1
Summary: Generate `click` commands from function docstrings.
Home-page: https://github.com/EpicWink/click-from-docstring
Author: Laurie O
Author-email: laurie_opperman@hotmail.com
License: MIT
Project-URL: Bugs, https://github.com/EpicWink/click-from-docstring/issues
Project-URL: Source, https://github.com/EpicWink/click-from-docstring
Keywords: click,docstring
Platform: UNKNOWN
Classifier: Development Status :: 1 - Planning
Classifier: Environment :: Console
Classifier: Intended Audience :: Developers
Classifier: License :: OSI Approved :: MIT License
Classifier: Natural Language :: English
Classifier: Operating System :: OS Independent
Classifier: Programming Language :: Python :: 3 :: Only
Classifier: Programming Language :: Python :: 3.5
Classifier: Programming Language :: Python :: 3.6
Classifier: Programming Language :: Python :: 3.7
Classifier: Programming Language :: Python :: 3.8
Classifier: Topic :: Software Development :: User Interfaces
Requires-Python: ~=3.5
Requires-Dist: click (~=7.0)
